cli/__init__.py
cli/biz.py
cli/main.py
cli/run.py
cli/templates/client.jinja2
cli/templates/clients.init.jinja2
cli/templates/config.jinja2
cli/templates/utils.jinja2
tests/__init__.py
tests/test_biz.py
tests/test_main.py
bali_cli-2.7.0.dist-info/LICENSE
bali_cli-2.7.0.dist-info/METADATA
bali_cli-2.7.0.dist-info/WHEEL
bali_cli-2.7.0.dist-info/entry_points.txt
bali_cli-2.7.0.dist-info/top_level.txt
bali_cli-2.7.0.dist-info/RECORD
