Metadata-Version: 2.1
Name: bali-cli
Version: 2.7.0
Summary: Simplify gRPC services and clients
Home-page: https://github.com/bali-framework/bali-cli
Author: Josh.Yu
Author-email: josh.yu_8@live.com
License: MIT
Platform: UNKNOWN
Requires-Dist: decamelize (==0.1.2)
Requires-Dist: grpcio (<=1.50.0,>=1.32.0)
Requires-Dist: grpcio-tools (<=1.50.0,>=1.32.0)
Requires-Dist: GitPython (<3.2dev,>=3.1.11)
Requires-Dist: jinja2 (>=2.11.2)
Requires-Dist: MarkupSafe (==2.0.1)
Requires-Dist: protobuf2pydantic (==2021.11.25)
Requires-Dist: pydantic (~=1.7)
Requires-Dist: typer (>=0.4)
